freedomrobotics_api/__init__.py
freedomrobotics_api/account.py
freedomrobotics_api/alert.py
freedomrobotics_api/api_handler.py
freedomrobotics_api/credentials.py
freedomrobotics_api/device.py
freedomrobotics_api/entity.py
freedomrobotics_api/helpers.py
freedomrobotics_api/op_deployment.py
freedomrobotics_api/op_deployment_service.py
freedomrobotics_api/token.py
freedomrobotics_api/user.py
freedomrobotics_api/zone.py
freedomrobotics_api/cli/__init__.py
freedomrobotics_api/cli/freedom.py
freedomrobotics_api/cli/commands/__init__.py
freedomrobotics_api/cli/commands/base.py
freedomrobotics_api/cli/commands/device.py
freedomrobotics_api/cli/commands/setup.py
freedomrobotics_api/tools/__init__.py
freedomrobotics_api/tools/buffering_tracer.py
freedomrobotics_api/tools/monitoring.py
freedomrobotics_api-1.2.0.dist-info/METADATA
freedomrobotics_api-1.2.0.dist-info/WHEEL
freedomrobotics_api-1.2.0.dist-info/entry_points.txt
freedomrobotics_api-1.2.0.dist-info/top_level.txt
freedomrobotics_api-1.2.0.dist-info/RECORD
