Metadata-Version: 2.1
Name: freedomrobotics-api
Version: 1.2.0
Requires-Dist: requests
Requires-Dist: Click
